django_public_id-2.2.1.dist-info/DESCRIPTION.rst
django_public_id-2.2.1.dist-info/METADATA
django_public_id-2.2.1.dist-info/RECORD
django_public_id-2.2.1.dist-info/WHEEL
django_public_id-2.2.1.dist-info/metadata.json
django_public_id-2.2.1.dist-info/top_level.txt
django_public_id-2.2.1.dist-info/zip-safe
public_id/__init__.py
public_id/fields.py
public_id/utils.py
