Metadata-Version: 2.0
Name: django-public-id
Version: 2.2.1
Summary: Long non-incremental IDs for public links. Essentially a compact form of UUID (22 bytes for 128-bit value)
Home-page: https://github.com/shantilabs/django-public-id
Author: Dmitrii Gerasimenko
Author-email: kiddima@gmail.com
License: UNKNOWN
Platform: UNKNOWN
Classifier: Programming Language :: Python
Classifier: Programming Language :: Python :: 2.7
Classifier: Programming Language :: Python :: 3.3
Classifier: Programming Language :: Python :: 3.4
Classifier: Programming Language :: Python :: 3.5
Classifier: Programming Language :: Python :: 3.6
Classifier: License :: OSI Approved :: BSD License
Classifier: Operating System :: OS Independent
Classifier: Framework :: Django
Classifier: Intended Audience :: Developers
